{
  "unlockedByDefault": true,
  "type": "irons_jewelry:necklace",
  "descriptionId": "pattern.irons_jewelry.simple_chain",
  "parts": [
    {
      "id": "irons_jewelry:chain_simple",
      "materialCost": 4,
      "drawOrder": 0
    }
  ],
  "bonuses": [
    {
      "bonus": "irons_jewelry:attribute_bonus",
      "parameter": "irons_jewelry:chain_simple",
      "quality": 1.0
    }
  ]
}
///give @p irons_jewelry:ring[irons_jewelry:jewelry_data={pattern:"irons_jewelry:gemset_ring",parts:{"irons_jewelry:band_gem":"irons_jewelry:silver","irons_jewelry:gem_pointy":"irons_jewelry:diamond"}}]